numbersapi_client/__init__.py
numbersapi_client/client.py
numbersapi_client/enums.py
numbersapi_client/exceptions.py
numbersapi_client/response_types.py
numbersapi_client-0.2.1.dist-info/WHEEL
numbersapi_client-0.2.1.dist-info/METADATA
numbersapi_client-0.2.1.dist-info/RECORD
